haglo/__init__.py
haglo/tiktok_timestamp.py
haglo-1.0.0.dist-info/METADATA
haglo-1.0.0.dist-info/WHEEL
haglo-1.0.0.dist-info/top_level.txt
haglo-1.0.0.dist-info/RECORD
