Metadata-Version: 2.1
Name: haglo
Version: 1.0.0
Summary: Tiktok
Author: haglo
Author-email: haglohd007@gmail.com
Keywords: python,tiktok,tiktokapi
Classifier: Development Status :: 1 - Planning
Classifier: Intended Audience :: Developers
Classifier: Programming Language :: Python :: 3
Classifier: Operating System :: Unix
Classifier: Operating System :: MacOS :: MacOS X
Classifier: Operating System :: Microsoft :: Windows
Requires-Dist: requests
Requires-Dist: datetime
